{
  "exams": [
    {
      "cpf": "03563117594",
      "type": "Eletrocardiograma",
      "date": "2021-05-10T23:55:20.814Z",
      "status": "Concluido",
      "hypotesis": "la la la",
      "image": "http://www.africau.edu/images/default/sample.pdf",
      "report": "",
      "report_status": "Aguardando laudo",
      "id": 1
    },
    {
      "cpf": "00000000001",
      "type": "Mapa",
      "date": "2021-05-12T00:00:00.000Z",
      "status": "Agendado",
      "hypotesis": "hiphip\n",
      "image": "",
      "report": "",
      "report_status": "Aguardando laudo",
      "id": 2
    },
    {
      "cpf": "00000000001",
      "type": "Mapa",
      "date": "2021-05-12T00:00:00.000Z",
      "status": "Cancelado",
      "hypotesis": "hiphip\n",
      "image": "",
      "report": "",
      "report_status": "Aguardando laudo",
      "id": 2
    },
    {
      "cpf": "00000000001",
      "type": "Mapa",
      "date": "2021-05-05T00:00:00.000Z",
      "status": "Agendado",
      "hypotesis": "hiphip\n",
      "image": "",
      "report": "",
      "report_status": "Aguardando laudo",
      "id": 3
    }
  ],
  "recommendations": [
    {
      "id": 1,
      "exam": "Ecocardiograma",
      "recommendations": "Recomendações para ecocardiograma."
    },
    {
      "id": 2,
      "exam": "Eletrocardiograma",
      "recommendations": "Recomendações para eletrocardiograma."
    },
    {
      "id": 3,
      "exam": "Mapa",
      "recommendations": "Recomendações para mapa."
    },
    {
      "id": 4,
      "exam": "Router",
      "recommendations": "Recomendações para router."
    }
  ]
}